ged_building_layout/__init__.py
ged_building_layout/cli.py
ged_building_layout/pipeline.py
ged_building_layout/step0_checks.py
ged_building_layout/step1_behavior.py
ged_building_layout/step2_basegraph.py
ged_building_layout/step3_transform.py
ged_building_layout/step4_prototype.py
ged_building_layout/step5_faged.py
ged_building_layout/viz_style.py
ged_building_layout-0.2.1.dist-info/METADATA
ged_building_layout-0.2.1.dist-info/WHEEL
ged_building_layout-0.2.1.dist-info/entry_points.txt
ged_building_layout-0.2.1.dist-info/top_level.txt
ged_building_layout-0.2.1.dist-info/RECORD
