Metadata-Version: 2.4
Name: ged-building-layout
Version: 0.2.1
Summary: construct graph representation for open-space public buildings, extract prototypes, and compute (n)GED/FaGED for layout-behavior retrieval.
Author: Song Guo
License: MIT
Project-URL: Homepage, https://github.com/songguoarchitect/GED-building-layout
Project-URL: Repository, https://github.com/songguoarchitect/GED-building-layout
Project-URL: Issues, https://github.com/songguoarchitect/GED-building-layout/issues
Keywords: graph-edit-distance,infomap,networkx,architecture,layout
Classifier: Programming Language :: Python :: 3
Classifier: Programming Language :: Python :: 3.10
Classifier: Programming Language :: Python :: 3.11
Classifier: Programming Language :: Python :: 3.12
Classifier: License :: OSI Approved :: MIT License
Requires-Python: >=3.10
Requires-Dist: numpy>=1.24
Requires-Dist: pandas>=2.0
Requires-Dist: networkx>=3.2
Requires-Dist: tqdm>=4.66
Requires-Dist: matplotlib>=3.8
Requires-Dist: scipy>=1.10
Requires-Dist: opencv-python>=4.8
Requires-Dist: shapely<2.1,>=1.8
Requires-Dist: infomap>=2.7
Provides-Extra: dev
Requires-Dist: pytest>=8; extra == "dev"
Requires-Dist: ruff>=0.6; extra == "dev"
Requires-Dist: build>=1.2; extra == "dev"
Requires-Dist: twine>=5.0; extra == "dev"
